castor/__init__.py
castor/alignment.py
castor/files_handling.py
castor/mount_alignment.py
castor/photometry.py
castor/preparation.py
castor/spectroscopy.py
castor/_console_scripts/__init__.py
castor/_console_scripts/align.py
castor/_console_scripts/align_spectra.py
castor/_console_scripts/exoplanet_analysis.py
castor/_console_scripts/pointing_analysis.py
castor/_console_scripts/prepare.py
castor/_console_scripts/rotate_spectra.py
castor/_console_scripts/wavelength_calibration.py
castor/data/instruments.yml
castor_orsay-2023.8.2.1.dist-info/LICENSE.txt
castor_orsay-2023.8.2.1.dist-info/METADATA
castor_orsay-2023.8.2.1.dist-info/WHEEL
castor_orsay-2023.8.2.1.dist-info/entry_points.txt
castor_orsay-2023.8.2.1.dist-info/top_level.txt
castor_orsay-2023.8.2.1.dist-info/RECORD
