Metadata-Version: 2.1
Name: castor-orsay
Version: 2023.8.2.1
Summary: Codes pour l’ASTronomie à ORsay
Home-page: https://github.com/coupole-orsay/castor
Author: Gabriel Pelouze, Aurélien Stcherbinine
Author-email: gabriel.pelouze@ias.u-psud.fr, aurelien.stcherbinine@ias.u-psud.fr
Classifier: Programming Language :: Python :: 3
Classifier: License :: OSI Approved :: MIT License
Classifier: Operating System :: OS Independent
Classifier: Intended Audience :: Science/Research
Classifier: Topic :: Scientific/Engineering :: Astronomy
Requires-Python: >=3.5
License-File: LICENSE.txt
Requires-Dist: python-dateutil (==2.8.2)
Requires-Dist: numpy (==1.25.2)
Requires-Dist: matplotlib (==3.7.2)
Requires-Dist: astropy (==5.3.1)
Requires-Dist: tqdm (==4.65.0)
Requires-Dist: astroalign (==2.4.2)
Requires-Dist: sep (==1.2.1)
Requires-Dist: PyYAML (==6.0.1)
Requires-Dist: opencv-python (==4.8.0.74)
Requires-Dist: scikit-image (==0.21.0)
Requires-Dist: scipy (==1.11.1)
